README.md
setup.py
quantdata/__init__.py
quantdata/analyzer.py
quantdata/client.py
quantdata/data_processor.py
quantdata/helpers.py
quantdata/parse.py
quantdata/quant.py
quantdata.egg-info/PKG-INFO
quantdata.egg-info/SOURCES.txt
quantdata.egg-info/dependency_links.txt
quantdata.egg-info/requires.txt
quantdata.egg-info/top_level.txt
quantdata/exception/__init__.py
quantdata/http/__init__.py
quantdata/model/__init__.py
quantdata/model/base.py
quantdata/model/ctpbee.py
quantdata/model/join_quant.py
quantdata/model/quantaxis.py
quantdata/model/rice_quant.py
quantdata/model/tqsdk.py
quantdata/model/vnpy.py
quantdata/operation/__init__.py