Metadata-Version: 1.0
Name: quantdata
Version: 0.2
Summary: quant data support of full platform
Home-page: UNKNOWN
Author: yutiansut && somewheve
Author-email: UNKNOWN
License: UNKNOWN
Platform: UNKNOWN
